{
  "$schema": "https://schema.management.azure.com/schemas/2015-01-01/deploymentParameters.json#",
  "contentVersion": "1.0.0.0",
  "parameters": {
    "emailAddress": {
      "value": "sec-warn@company.org"
    },
    "actionGroupName": {
      "value": "ag-warn-security"
    },
    "actionGroupShortName": {
      "value": "ag-warn-sec"
    },
    "smsPhoneNumber": {
      "value": "9999999999"
    },
    "voicePhoneNumber": {
      "value": "9999999999"
    },
    "azAppPushId": {
      "value": "sec-warn@company.org"
    }
  }
}
